synodic_utilities-0.1.1.dev9.dist-info/METADATA
synodic_utilities-0.1.1.dev9.dist-info/WHEEL
synodic_utilities-0.1.1.dev9.dist-info/licenses/LICENSE.md
synodic_utilities/__init__.py
synodic_utilities/exception.py
synodic_utilities/plugin.py
synodic_utilities/py.typed
synodic_utilities/subprocess.py
synodic_utilities/utility.py
synodic_utilities-0.1.1.dev9.dist-info/RECORD
