Metadata-Version: 2.1
Name: synodic-utilities
Version: 0.1.1.dev9
Summary: Synodic python utility library
Home-page: https://github.com/Synodic-Software/Synodic-Utilities
Author-Email: Asher Norland <asher.norland@synodic.software>
License: MIT
Project-URL: Homepage, https://github.com/Synodic-Software/Synodic-Utilities
Project-URL: Repository, https://github.com/Synodic-Software/Synodic-Utilities
Requires-Python: >=3.12
